<?xml version="1.0" encoding="UTF-8"?>
<object id="00000000063" name="Intelligence" objectType="test" pos="12">
<fact comp="n" edit="y" id="00000000017" label="Priority" pos1="999" pos2="999" relTo="00000000063" version="1">
<str_fact/>
</fact>
<fact comp="n" edit="y" id="00000000064" label="Source" pos1="999" pos2="999" relTo="00000000063" version="1">
<str_fact/>
</fact>
<fact comp="n" edit="y" id="00000000065" label="Time" pos1="999" pos2="999" relTo="00000000063" version="1">
<date_fact/>
</fact>
<fact comp="n" edit="y" id="00000000043" label="Description" pos1="999" pos2="999" relTo="00000000063" version="1">
<str_fact/>
</fact>
<fact comp="n" edit="y" id="00000000062" label="Status" pos1="999" pos2="999" relTo="00000000063" version="1">
<str_fact/>
</fact>
</object>
