<?xml version="1.0" encoding="UTF-8"?>
<object id="00000000149" name="Subject" objectType="test" pos="47">
<fact comp="n" edit="y" id="00000000013" label="ID" pos1="999" pos2="999" relTo="00000000149" version="1">
<str_fact/>
</fact>
<fact comp="n" edit="y" id="00000000029" label="Height" pos1="999" pos2="999" relTo="00000000149" version="1">
<num_fact antdec="0" max="1.0E8" min="0.0"/>
</fact>
<fact comp="n" edit="y" id="00000000150" label="Weight" pos1="999" pos2="999" relTo="00000000149" version="1">
<num_fact antdec="0" max="1.0E8" min="0.0"/>
</fact>
<fact comp="n" edit="y" id="00000000151" label="Eyes" pos1="999" pos2="999" relTo="00000000149" version="1">
<str_fact/>
</fact>
<fact comp="n" edit="y" id="00000000152" label="Hair" pos1="999" pos2="999" relTo="00000000149" version="1">
<str_fact/>
</fact>
<fact comp="n" edit="y" id="00000000153" label="Build" pos1="999" pos2="999" relTo="00000000149" version="1">
<str_fact/>
</fact>
<fact comp="n" edit="y" id="00000000154" label="Physical" pos1="999" pos2="999" relTo="00000000149" version="1">
<str_fact/>
</fact>
<fact comp="n" edit="y" id="00000000155" label="Psychic" pos1="999" pos2="999" relTo="00000000149" version="1">
<str_fact/>
</fact>
<fact comp="n" edit="y" id="00000000014" label="Remarks" pos1="999" pos2="999" relTo="00000000149" version="1">
<num_fact antdec="0" max="1.0E8" min="0.0"/>
</fact>
<fact comp="n" edit="y" id="00000000018" label="Status" pos1="999" pos2="999" relTo="00000000149" version="1">
<num_fact antdec="0" max="1.0E8" min="0.0"/>
</fact>
</object>
